{
  "project": "diminishing-returns",
  "increment": 2,
  "assembled": "2026-07-12 (Ensemble session 02; every VERIFIED figure checked first-hand by the conductor against the upstream instrument's committed record)",
  "tier_note": "VERIFIED = from the research wing's gauntleted instrument 013 'The Floor' (field-research/works/2026-07-09-the-floor/) and its claims ledger; IMAGINED = the game framing, marked. The engine must compute all outcomes from the numbers below at runtime — nothing about winning or losing may be hardcoded.",
  "verified": {
    "subject": "Google's data-center fleet, as disclosed in Google's own environmental reports",
    "floor": 1.0,
    "floor_meaning": "PUE = total facility energy / IT-equipment energy; IT energy is a subset of total, so the ratio cannot fall below 1.0 (The Green Grid; ISO/IEC 30134-2:2016).",
    "breakeven_formula": "required_PUE = base_PUE / (1 + growth); base_PUE is the PRIOR year's fleet PUE (per-year base — 1.10 for the 2024 round, 1.09 for the 2025 round)",
    "winnable_condition": "a round is winnable in principle iff required_PUE >= floor, i.e. growth_pct <= (base_PUE - 1.0) * 100 (10% at base 1.10; 9% at base 1.09)",
    "rounds": [
      {
        "year": 2023,
        "base_pue": 1.1,
        "growth_pct": 17,
        "growth_quote": "compared to 17% growth in the prior year",
        "growth_scope": "total data center electricity consumption (2025 report's wording, describing 2023)",
        "achieved_fleet_pue_that_year": 1.1
      },
      {
        "year": 2024,
        "base_pue": 1.1,
        "growth_pct": 27,
        "growth_quote": "our total data center electricity consumption grew by 27% in 2024, compared to 17% growth in the prior year",
        "growth_scope": "total data center electricity consumption (2025 report, FY2024)",
        "achieved_fleet_pue_that_year": 1.09
      },
      {
        "year": 2025,
        "base_pue": 1.09,
        "growth_pct": 37,
        "growth_quote": "…our total electricity consumption grew by 37% in 2025, up from 27% in 2024",
        "growth_scope": "TOTAL electricity consumption (2026 report, FY2025) — a wider wording than the 2025 report's 'data center' framing; quoted exactly as each source states it, not conflated (upstream wording-shift flag carried)",
        "achieved_fleet_pue_that_year": 1.09
      }
    ],
    "fleet_pue_series": {
      "2019-2023": 1.1,
      "2024": 1.09,
      "2025": 1.09,
      "note": "2019–2023 all 1.10 (2024 report data table); 2024 = 1.09 ('for the first time in six years... dropped below 1.10 to 1.09', 2025 report); 2025 = 1.09 (2026 report: 'a 2025 average annual PUE of 1.09... 83% less overhead energy than the industry average')."
    },
    "sources": [
      {
        "id": "google_2024_env_report",
        "covers": "fleet PUE 2019–2023",
        "url": "https://www.smartenergydecisions.com/wp-content/uploads/2025/04/google-2024-environmental-report.pdf"
      },
      {
        "id": "google_2025_env_report",
        "covers": "FY2024: PUE 1.09; growth 27% (and 17% prior year)",
        "url": "https://www.smartenergydecisions.com/wp-content/uploads/2025/07/google-2025-environmental-report-1.pdf",
        "official": "https://sustainability.google/reports/google-2025-environmental-report"
      },
      {
        "id": "google_2026_env_report",
        "covers": "FY2025: PUE 1.09; growth 37%",
        "url": "https://storage.googleapis.com/gweb-mobius-cdn/sustainability/uploads/7f477eb723fe0c23d03f94b90a08882b9f28187d.pdf",
        "official": "https://sustainability.google/google-2026-environmental-report"
      },
      {
        "id": "upstream_instrument_013",
        "covers": "the breakeven arithmetic, the floor, all caveats — fully gauntleted upstream",
        "url": "https://github.com/frankbueltge/field-research/tree/main/works/2026-07-09-the-floor"
      }
    ],
    "caveats_carried": [
      "NOT a concealment claim: Google discloses the growth figures openly in the same reports; the critique upstream concerns framing (efficiency foregrounded as counterweight to absolutes), and this game dramatizes that arithmetic — it accuses nobody of hiding numbers.",
      "Fleet PUE covers Google-owned-and-operated campuses only, not leased/colocation facilities.",
      "The 27%-vs-37% figures carry a wording shift between the two reports ('data center electricity' vs 'total electricity') — quoted exactly per source, not conflated.",
      "Per-year base discipline: each round's required PUE divides the PRIOR year's fleet PUE (the upstream seed correction, session 18)."
    ]
  },
  "imagined": {
    "marked": true,
    "elements": "The dial-as-opponent, the rounds-as-game, the effort resistance curve, and every word of the game's voice are dramatization — a choice, not a fact about the world. The honesty panel on the work must say so. In particular: 'you cannot win' is NOT a premise of this piece — it is whatever the engine computes from the disclosed numbers above; if a future disclosed year shows growth at or below the winnable threshold, this same engine declares that round winnable."
  },
  "sourced_companies": {
    "tier": "SOURCED — the collective's own research (Ensemble session 03, 2026-07-12), primary company disclosures, per-figure tier noted. Gathered BEFORE the engine's conclusion was extended (Kritiker condition 3); the engine computes whatever these numbers yield.",
    "meta": {
      "display_name": "Meta",
      "pue_series": {
        "2020": 1.1,
        "2021": 1.09,
        "2022": 1.08,
        "2023": 1.08,
        "2024": 1.08
      },
      "pue_quote": "PUE (data center energy efficiency) 1.10 1.09 1.08 1.08 1.08",
      "dc_electricity_mwh": {
        "2022": 11167416,
        "2023": 14975435,
        "2024": 18061781
      },
      "rounds": [
        {
          "year": 2023,
          "base_pue": 1.08,
          "growth_pct": 34.1,
          "growth_arithmetic": "(14975435-11167416)/11167416 = +34.1%"
        },
        {
          "year": 2024,
          "base_pue": 1.08,
          "growth_pct": 20.6,
          "growth_arithmetic": "(18061781-14975435)/14975435 = +20.6%"
        }
      ],
      "source": {
        "name": "Meta 2025 Environmental Data Index",
        "url": "https://sustainability.atmeta.com/wp-content/uploads/2025/10/Meta_2025-Environmental-Data-Index.pdf"
      },
      "verification_note": "Researcher-FETCHED via text-proxy of the primary PDF; conductor spot-check blocked by the PDF's text encoding — the +34.1% independently corroborated by DataCenterDynamics ('+34%'). Honest tier: SOURCED, one figure-set, proxy-read.",
      "caveats": [
        "'Data centers total' combines owned AND leased facilities — a genuinely data-center-scoped figure (cleaner than Microsoft's org-wide number).",
        "UNCONFIRMED whether the PUE 1.08 covers the same owned+leased footprint (industry convention often excludes leased/colo from fleet PUE) — an open scope question, stated, not resolved.",
        "Meta runs closest to the floor of all four companies: at 1.08 the winnability threshold is 8% growth; total remaining headroom is (1.08-1.00)/1.08 = 7.4%, once."
      ]
    },
    "microsoft": {
      "display_name": "Microsoft",
      "pue_series": {
        "FY24": 1.16,
        "FY25": 1.17
      },
      "pue_quote": "Global PUE: FY24 1.16, FY25 1.17 — 'based on datacenters that Microsoft fully owns and controls and that were operational for 12 months at the time of calculation'",
      "pue_direction_note": "Efficiency WORSENED FY24→FY25 (1.16→1.17): the dial's starting point itself slid backwards — disclosed by the subject, rendered as found.",
      "org_electricity_mwh": {
        "FY22": 18153454,
        "FY23": 23567502,
        "FY24": 29829540
      },
      "rounds": [
        {
          "year": "FY2024",
          "base_pue": 1.16,
          "growth_pct": 26.6,
          "growth_arithmetic": "(29829540-23567502)/23567502 = +26.6%",
          "base_pue_note": "FY23 fleet PUE is not disclosed; this round uses FY24's own reported 1.16 — a disclosed-inputs approximation, marked on the referee card."
        }
      ],
      "sources": [
        {
          "name": "Microsoft datacenter sustainability/efficiency page (PUE)",
          "url": "https://datacenters.microsoft.com/sustainability/efficiency/",
          "tier": "FETCHED first-hand by the conductor"
        },
        {
          "name": "Microsoft Environmental Data Fact Sheets 2024/2025 (electricity, Table 6 'Energy consumption within the organization')",
          "url": "https://cdn-dynmedia-1.microsoft.com/is/content/microsoftcorp/microsoft/msc/documents/presentations/CSR/2025-Microsoft-Environmental-Data-Fact-Sheet-PDF.pdf",
          "tier": "Researcher-FETCHED via text-proxy; growth ~27% matches press corroboration"
        }
      ],
      "caveats": [
        "SCOPE MISMATCH, rendered loudly: the PUE covers owned-and-controlled datacenters only; the electricity growth is ORG-WIDE (whole company, GRI 302-1 style) — Microsoft does not publish a datacenter-only consumption series beside its PUE. The round is playable only with this asterisk on its face.",
        "Fiscal years (July–June), not calendar years — never mix with Google/Meta calendar-year rounds without saying so."
      ]
    },
    "aws": {
      "display_name": "Amazon / AWS",
      "pue_series_as_reported": {
        "reported 2024": 1.15,
        "reported 2025": 1.14
      },
      "pue_quote": "In 2025, our data centers reported an average global PUE of 1.14 which is an improvement compared to 1.15 reported in 2024.",
      "pue_ambiguity": "Amazon labels PUE by REPORT year; whether '2025' means data-year 2024 is not resolvable from the primary text — stated, not guessed.",
      "consumption_disclosure": "NONE. The 2024 Sustainability Report's accessible-tables appendix (GRI/SASB-style) contains carbon and renewables tables but NO absolute electricity/energy consumption figure — for AWS or for Amazon total. Checked at the primary source; corroborated by press coverage of investor pressure for exactly this disclosure.",
      "sources": [
        {
          "name": "AWS cloud sustainability page (PUE)",
          "url": "https://sustainability.aboutamazon.com/products-services/aws-cloud",
          "tier": "Researcher-FETCHED via text-proxy"
        },
        {
          "name": "Amazon 2024 Sustainability Report — accessible tables (absence of consumption figures confirmed)",
          "url": "https://sustainability.aboutamazon.com/2024-sustainability-report-accessible-tables.pdf",
          "tier": "Researcher-FETCHED via text-proxy (absence check)"
        }
      ],
      "no_round": "An efficiency ratio without a consumption figure cannot form a round: required_PUE = base/(1+growth) has no growth. AWS's round is rendered LOCKED — 'no disclosure, no game' — the finding is the absence."
    }
  }
}
